Workbook
Name aporte: Planilha1!$D$15:$D$15
Name patrimonio: Planilha1!$D$18:$D$18
Name qtd_anos: Planilha1!$D$16:$D$16
Name redimento_carteira: Planilha1!$D$11:$D$11
Name salario: Planilha1!$D$10:$D$10
Name sugestao_investimento: Planilha1!$D$12:$D$12
Name taxa_mensal: Planilha1!$D$17:$D$17

Sheet Planilha1
B9: Configurações
B10: Salário | D10: 2000
B11: Redimento Carteira | D11: 0.006
B12: Sugestão de investimento (30%) | D12: =D10*30% -> 600
B14: Investimento Mensal
B15: Quanto investir por mês? | D15: 200
B16: Por Quantos Anos ? | D16: 10
B17: Taxa de Rendimentos mensal? | D17: 0.0108
B18: Patrimônio acumulado? | D18: {=FV(taxa_mensal,qtd_anos*12,aporte*-1)} -> 48691.533
B19: Dividendos Mensais? | D19: {=patrimonio*redimento_carteira} -> 292.1492
B21: Cenários | D21: Dividendo
A22: 2 | B22: Quantos em 2 Anos ? | C22: =FV($D$17,$A22*12,$D$15*-1) -> 5446.1727 | D22: {=C22*redimento_carteira} -> 32.677036
A23: 5 | B23: Quantos em 5 Anos ? | C23: =FV($D$17,$A23*12,$D$15*-1) -> 16760.804 | D23: {=C23*redimento_carteira} -> 100.56482
A24: 10 | B24: Quantos em 10 Anos ? | C24: =FV($D$17,$A24*12,$D$15*-1) -> 48691.533 | D24: {=C24*redimento_carteira} -> 292.1492
A25: 20 | B25: Quantos em 20 Anos ? | C25: =FV($D$17,$A25*12,$D$15*-1) -> 225409.8 | D25: {=C25*redimento_carteira} -> 1352.4588
A26: 30 | B26: Quantos em 30 Anos ? | C26: =FV($D$17,$A26*12,$D$15*-1) -> 866780.96 | D26: {=C26*redimento_carteira} -> 5200.6858
B28: PERFIL | C28: Agressivo
B29: Valor a ser investido por mês | C29: {=aporte} -> 200
B31: TIPO DE FII | C31: Percentual Sugerido | D31: Valores
B32: PAPEL | C32: =VLOOKUP($C28&"-"&B32,Planilha2!$A:$D,4,FALSE) -> 0.5 | D32: =C32*$C$29 -> 100
B33: TIOJOLO | C33: =VLOOKUP($C28&"-"&B33,Planilha2!$A:$D,4,FALSE) -> 0.1 | D33: =C33*$C$29 -> 20
B34: HÍBRIDOS | C34: =VLOOKUP($C$28&"-"&B34,Planilha2!$A:$D,4,FALSE) -> 0.05 | D34: =C34*$C$29 -> 10
B35: FOFs | C35: =VLOOKUP($C$28&"-"&B35,Planilha2!$A:$D,4,FALSE) -> 0.05 | D35: =C35*$C$29 -> 10
B36: DESENVOLVIMENTOS | C36: =VLOOKUP($C28&"-"&B36,Planilha2!$A:$D,4,FALSE) -> 0.2 | D36: =C36*$C$29 -> 40
B37: HOTELARIAS | C37: =VLOOKUP($C28&"-"&B37,Planilha2!$A:$D,4,FALSE) -> 0.1 | D37: =C37*$C$29 -> 20
D38: =SUM(D32:D37) -> 200

Sheet Planilha2
A2: CHAVE | B2: PERFIL | C2: TIPO DE FII | D2: %
A3: =$B3&"-"&C3 -> Conservador-PAPEL | B3: Conservador | C3: PAPEL | D3: 0.3
A4: =$B4&"-"&C4 -> Conservador-TIOJOLO | B4: Conservador | C4: TIOJOLO | D4: 0.5
A5: =$B5&"-"&C5 -> Conservador-HÍBRIDOS | B5: Conservador | C5: HÍBRIDOS | D5: 0.1
A6: =$B6&"-"&C6 -> Conservador-FOFs | B6: Conservador | C6: FOFs | D6: 0.1
A7: =$B7&"-"&C7 -> Conservador-DESENVOLVIMENTOS | B7: Conservador | C7: DESENVOLVIMENTOS | D7: 0
A8: =$B8&"-"&C8 -> Conservador-HOTELARIAS | B8: Conservador | C8: HOTELARIAS | D8: 0
A9: =$B9&"-"&C9 -> Moderado-PAPEL | B9: Moderado | C9: PAPEL | D9: 0.32
A10: =$B10&"-"&C10 -> Moderado-TIOJOLO | B10: Moderado | C10: TIOJOLO | D10: 0.35
A11: =$B11&"-"&C11 -> Moderado-HÍBRIDOS | B11: Moderado | C11: HÍBRIDOS | D11: 0.08
A12: =$B12&"-"&C12 -> Moderado-FOFs | B12: Moderado | C12: FOFs | D12: 0.05
A13: =$B13&"-"&C13 -> Moderado-DESENVOLVIMENTOS | B13: Moderado | C13: DESENVOLVIMENTOS | D13: 0.1
A14: =$B14&"-"&C14 -> Moderado-HOTELARIAS | B14: Moderado | C14: HOTELARIAS | D14: 0.1
... A20: =$B20&"-"&C20 -> Agressivo-HOTELARIAS | B20: Agressivo | C20: HOTELARIAS | D20: 0.1
